add_skill/__init__.py
add_skill-0.1.0.dist-info/METADATA
add_skill-0.1.0.dist-info/WHEEL
add_skill-0.1.0.dist-info/entry_points.txt
add_skill-0.1.0.dist-info/RECORD
