Metadata-Version: 2.4
Name: add-skill
Version: 0.1.0
Summary: Add Claude Code skills from GitHub to your project
License-Expression: MIT
Requires-Python: >=3.10
Requires-Dist: agent-resources>=0.1.0
